README.rst
setup.py
powershift_image.egg-info/PKG-INFO
powershift_image.egg-info/SOURCES.txt
powershift_image.egg-info/dependency_links.txt
powershift_image.egg-info/entry_points.txt
powershift_image.egg-info/requires.txt
powershift_image.egg-info/top_level.txt
src/powershift/__init__.py
src/powershift/image/__init__.py
src/powershift/image/scripts/alive.sh
src/powershift/image/scripts/assemble.sh
src/powershift/image/scripts/exec.sh
src/powershift/image/scripts/jobs.sh
src/powershift/image/scripts/migrate.sh
src/powershift/image/scripts/ready.sh
src/powershift/image/scripts/run.sh
src/powershift/image/scripts/setup.sh
src/powershift/image/scripts/shell.sh
src/powershift/image/scripts/verify.sh